odoo/addons/account_cutoff_accrual_order_stock_base/README.rst
odoo/addons/account_cutoff_accrual_order_stock_base/__init__.py
odoo/addons/account_cutoff_accrual_order_stock_base/__manifest__.py
odoo/addons/account_cutoff_accrual_order_stock_base/i18n/account_cutoff_accrual_order_stock_base.pot
odoo/addons/account_cutoff_accrual_order_stock_base/i18n/fr.po
odoo/addons/account_cutoff_accrual_order_stock_base/i18n/it.po
odoo/addons/account_cutoff_accrual_order_stock_base/models/__init__.py
odoo/addons/account_cutoff_accrual_order_stock_base/models/account_cutoff.py
odoo/addons/account_cutoff_accrual_order_stock_base/readme/CONTRIBUTORS.rst
odoo/addons/account_cutoff_accrual_order_stock_base/readme/DESCRIPTION.rst
odoo/addons/account_cutoff_accrual_order_stock_base/static/description/icon.png
odoo/addons/account_cutoff_accrual_order_stock_base/static/description/index.html
odoo/addons/account_cutoff_accrual_order_stock_base/views/account_cutoff_view.xml
odoo_addon_account_cutoff_accrual_order_stock_base-16.0.1.0.0.4.dist-info/METADATA
odoo_addon_account_cutoff_accrual_order_stock_base-16.0.1.0.0.4.dist-info/WHEEL
odoo_addon_account_cutoff_accrual_order_stock_base-16.0.1.0.0.4.dist-info/top_level.txt
odoo_addon_account_cutoff_accrual_order_stock_base-16.0.1.0.0.4.dist-info/RECORD
